easyaipy/__init__.py
easyaipy/easyai.py
easyaipy/utils.py
easyaipy-0.1.3.dist-info/LICENSE
easyaipy-0.1.3.dist-info/METADATA
easyaipy-0.1.3.dist-info/WHEEL
easyaipy-0.1.3.dist-info/top_level.txt
easyaipy-0.1.3.dist-info/RECORD
