Metadata-Version: 2.2
Name: easyaipy
Version: 0.1.3
Summary: EasyAIPy allows extracting precise variables from AI API responses.
Home-page: https://github.com/martinyanev94/easyaipy
Author: Martin Yanev
Author-email: mpyanev@gmail.com
Classifier: Programming Language :: Python :: 3
Classifier: License :: OSI Approved :: MIT License
Classifier: Operating System :: OS Independent
Requires-Python: >=3.6
License-File: LICENSE
Requires-Dist: openai
Dynamic: author
Dynamic: author-email
Dynamic: classifier
Dynamic: description
Dynamic: description-content-type
Dynamic: home-page
Dynamic: requires-dist
Dynamic: requires-python
Dynamic: summary
